smart_airdrop_claimer/__init__.py
smart_airdrop_claimer/base.py
smart_airdrop_claimer-0.1.2.dist-info/LICENSE
smart_airdrop_claimer-0.1.2.dist-info/METADATA
smart_airdrop_claimer-0.1.2.dist-info/WHEEL
smart_airdrop_claimer-0.1.2.dist-info/top_level.txt
smart_airdrop_claimer-0.1.2.dist-info/RECORD
